{"slug":"sailor","name":"Sailor","boosts":[["dex","str"],["cha","con","dex","int","str","wis"]],"trainedSkills":["athletics"],"trainedLore":["Sailing Lore"],"grantedFeat":{"name":"Underwater Marauder","slug":"underwater-marauder","level":1},"traits":{},"rules":[],"description":"You heard the call of the sea from a young age. Perhaps you signed onto a merchant's vessel, joined the navy, or even fell in with a crew of pirates and scalawags.\n\nChoose two attribute boosts. One must be to Strength or Dexterity, and one is a free attribute boost.\n\nYou're trained in the Athletics skill and the Sailing Lore skill. You gain the skill feat.","publication":{"license":"ORC","remaster":true,"title":"Pathfinder Player Core"}}