{"slug":"martial-experience","name":"Martial Experience","level":5,"category":"ancestry","prerequisites":[],"actionType":"passive","actions":null,"maxTakeable":null,"traits":{"value":["elf"]},"rules":[{"hideIfDisabled":true,"key":"FlatModifier","predicate":[{"lte":["self:level",10]}],"selector":"strike-attack-roll","type":"proficiency","value":"@actor.level"},{"key":"ActiveEffectLike","path":"system.proficiencies.attacks.unarmed.rank","mode":"upgrade","value":1,"predicate":[{"gte":["self:level",11]}],"phase":"beforeDerived"},{"key":"ActiveEffectLike","path":"system.proficiencies.attacks.simple.rank","mode":"upgrade","value":1,"predicate":[{"gte":["self:level",11]}],"phase":"beforeDerived"},{"key":"ActiveEffectLike","path":"system.proficiencies.attacks.martial.rank","mode":"upgrade","value":1,"predicate":[{"gte":["self:level",11]}],"phase":"beforeDerived"},{"key":"ActiveEffectLike","path":"system.proficiencies.attacks.advanced.rank","mode":"upgrade","value":1,"predicate":[{"gte":["self:level",11]}],"phase":"beforeDerived"}],"description":"You've crossed blades with a wide variety of foes wielding a wide variety of weapons, and you've learned the basics of fighting with nearly any of them. When wielding a weapon you aren't proficient with, treat your level as your proficiency bonus.\n\nAt 11th level, you become trained in all weapons.","publication":{"license":"ORC","remaster":true,"title":"Pathfinder Player Core"}}