{"slug":"unified-theory","name":"Unified Theory","level":15,"category":"skill","prerequisites":[{"type":"skill","skill":"arcana","rank":"4"}],"actionType":"passive","actions":null,"maxTakeable":null,"traits":{"value":["general","skill"]},"rules":[],"description":"You understand the common underpinnings of the four traditions of magic and magical essences, allowing you to understand them all through an arcane lens. Whenever you use a skill action or a skill feat that requires a Nature, Occultism, or Religion check, depending on the magic tradition, you can use Arcana instead. If you would normally take a penalty or have a higher DC for using Arcana on other magic (such as when using Identify Magic), you no longer do so.","publication":{"license":"ORC","remaster":true,"title":"Pathfinder Player Core"}}