{"slug":"command","name":"Command","level":1,"traditions":["arcane","divine","occult"],"time":"2","range":"30 feet","area":null,"targets":"1 creature","duration":"until the end of the target's next turn","defense":{"statistic":"will","basic":false},"damage":[],"heightening":{"levels":{"5":{"target":{"value":"10 creatures"}}},"type":"fixed"},"traits":{"value":["auditory","concentrate","linguistic","manipulate","mental"]},"rules":[],"description":"You shout a command that's hard to ignore. You can command the target to approach you, run away (as if it had the condition), release what it's holding, drop , or stand in place. It can't or take any reactions until it has obeyed your command. The effects depend on the target's Will save.\n\nSuccess The creature is unaffected.\n\nFailure For the first action on its next turn, the creature must use a single action to do as you command.\n\nCritical Failure The target must use all its actions on its next turn to obey your command.\n\nHeightened (5th) You can target up to 10 creatures.","publication":{"license":"ORC","remaster":true,"title":"Pathfinder Player Core"}}