{"slug":"dazzling-flash","name":"Dazzling Flash","level":1,"traditions":[],"time":"2","range":"","area":{"type":"cone","value":15},"targets":"","duration":"","defense":{"statistic":"fortitude","basic":false},"damage":[],"heightening":{"levels":{"3":{"area":{"type":"cone","value":"30"}}},"type":"fixed"},"traits":{"rarity":"uncommon","value":["cleric","concentrate","focus","light","manipulate","visual"]},"rules":[],"description":"You raise your religious symbol and create a blinding flash of light. Each creature in the area must attempt a Fortitude save.\n\nCritical Success The creature is unaffected.\n\nSuccess The creature is for 1 round.\n\nFailure The creature is for 1 round and Dazzled for 1 minute. The creature can spend an Interact action rubbing its eyes to end the Blinded condition.\n\nCritical Failure The creature is Blinded for 1 round and Dazzled for 1 hour.\n\nHeightened (3rd) The area increases to a 30-foot cone.","publication":{"license":"ORC","remaster":true,"title":"Pathfinder Player Core"}}